boxdb/FileWriteup.py
boxdb/__init__.py
boxdb/auth.py
boxdb/basic_commands.py
boxdb/checkups.py
boxdb/columns.py
boxdb/create.py
boxdb/logs.py
boxdb/readtable.py
boxdb/rows.py
boxdb/settings.py
boxdb/support.py
boxdb-0.9.dist-info/METADATA
boxdb-0.9.dist-info/WHEEL
boxdb-0.9.dist-info/top_level.txt
boxdb-0.9.dist-info/RECORD
