Metadata-Version: 2.1
Name: boxdb
Version: 0.9
Summary: Make Your own personal database liter than others
Home-page: https://github.com/kshitij1235/boxdb
Author: kshitij jathar
Author-email: kshitijjathar7@gmail.com
License: MIT
Project-URL: Bug Tracker, https://github.com/kshitij1235/boxdb/issues
Keywords: database
Platform: UNKNOWN
Classifier: Intended Audience :: Education
Classifier: Operating System :: Microsoft :: Windows :: Windows 10
Classifier: License :: OSI Approved :: MIT License
Classifier: Programming Language :: Python :: 3.5
Classifier: Programming Language :: Python :: 3.6
Classifier: Programming Language :: Python :: 3.7
Classifier: Programming Language :: Python :: 3.8
Requires-Dist: tabulate
Requires-Dist: filemod
Requires-Dist: colorama
